sqlargon/__init__.py
sqlargon/_version.py
sqlargon/db.py
sqlargon/imports.py
sqlargon/mixins.py
sqlargon/orm.py
sqlargon/pagination.py
sqlargon/py.typed
sqlargon/repository.py
sqlargon/settings.py
sqlargon/tracker.py
sqlargon/types/__init__.py
sqlargon/types/datetime.py
sqlargon/types/json.py
sqlargon/types/pydantic.py
sqlargon/types/uuid.py
sqlargon/uow.py
sqlargon/utils.py
sqlargon-0.6.12.dist-info/METADATA
sqlargon-0.6.12.dist-info/WHEEL
sqlargon-0.6.12.dist-info/licenses/LICENSE
sqlargon-0.6.12.dist-info/RECORD
