Metadata-Version: 2.4
Name: sqlargon
Version: 0.6.12
Summary: SQLAlchemy utils for Postgres and Sqlite
License-File: LICENSE
Author: Radzim Kowalow
Author-email: rarha_eu@protonmail.com
Requires-Python: >=3.8.1,<4.0
Classifier: Programming Language :: Python :: 3
Classifier: Programming Language :: Python :: 3.9
Classifier: Programming Language :: Python :: 3.10
Classifier: Programming Language :: Python :: 3.11
Classifier: Programming Language :: Python :: 3.12
Classifier: Programming Language :: Python :: 3.13
Classifier: Programming Language :: Python :: 3.14
Provides-Extra: all
Provides-Extra: opentelemetry
Provides-Extra: orjson
Requires-Dist: aiosqlite (>=0.19.0,<0.20.0)
Requires-Dist: alembic (>=1.13.1,<2.0.0)
Requires-Dist: asyncpg (<1.0)
Requires-Dist: opentelemetry-instrumentation-sqlalchemy ; extra == "all" or extra == "opentelemetry"
Requires-Dist: orjson ; extra == "all" or extra == "orjson"
Requires-Dist: pydantic (>=2.0,<3)
Requires-Dist: pydantic-settings (>=2.1.0,<3.0.0)
Requires-Dist: sqlakeyset (>=2.0.1716332987,<3.0.0)
Requires-Dist: sqlalchemy (>2.0,<3)
